pyapi/__init__.py
pyapi/__main__.py
pyapi/_version.py
pyapi/aexpy_api_processor.py
pyapi/api_processor.py
pyapi/app.py
pyapi/cli.py
pyapi/color.py
pyapi/config.py
pyapi/constants.py
pyapi/git.py
pyapi/model.py
pyapi/py.typed
pyapi/utils.py
pyapi_checker-0.12.0.dist-info/METADATA
pyapi_checker-0.12.0.dist-info/WHEEL
pyapi_checker-0.12.0.dist-info/entry_points.txt
pyapi_checker-0.12.0.dist-info/licenses/LICENSE
pyapi_checker-0.12.0.dist-info/RECORD
