Metadata-Version: 2.4
Name: pyapi-checker
Version: 0.12.0
Summary: Tool for checking for breaking changes in Python APIs
Project-URL: Source code, https://github.com/palantir/pyapi-checker
Author-email: Benjamin Lowry <benjaminpaullowry.appdev@gmail.com>
License-Expression: Apache-2.0
License-File: LICENSE
Classifier: Programming Language :: Python
Classifier: Programming Language :: Python :: 3
Classifier: Programming Language :: Python :: 3 :: Only
Classifier: Programming Language :: Python :: 3.12
Classifier: Programming Language :: Python :: 3.13
Classifier: Typing :: Typed
Requires-Python: >=3.12
Requires-Dist: aexpy
Requires-Dist: pip
Requires-Dist: pydantic
Requires-Dist: pyyaml
Requires-Dist: tomli
Requires-Dist: typer
